hmcalc/__init__.py
hmcalc/_utils.py
hmcalc/change.py
hmcalc/compare.py
hmcalc/percent.py
hmcalc/rounding.py
hmcalc/trend.py
tests/test_change.py
tests/test_compare.py
tests/test_percent.py
tests/test_rounding.py
tests/test_trend.py
venv/Lib/site-packages/easy_install.py
venv/Lib/site-packages/six.py
venv/Lib/site-packages/typing_extensions.py
venv/Lib/site-packages/bleach/__init__.py
venv/Lib/site-packages/bleach/callbacks.py
venv/Lib/site-packages/bleach/css_sanitizer.py
venv/Lib/site-packages/bleach/html5lib_shim.py
venv/Lib/site-packages/bleach/linkifier.py
venv/Lib/site-packages/bleach/parse_shim.py
venv/Lib/site-packages/bleach/sanitizer.py
venv/Lib/site-packages/bleach/_vendor/__init__.py
venv/Lib/site-packages/bleach/_vendor/parse.py
venv/Lib/site-packages/bleach/_vendor/html5lib/__init__.py
venv/Lib/site-packages/bleach/_vendor/html5lib/_ihatexml.py
venv/Lib/site-packages/bleach/_vendor/html5lib/_inputstream.py
venv/Lib/site-packages/bleach/_vendor/html5lib/_tokenizer.py
venv/Lib/site-packages/bleach/_vendor/html5lib/_utils.py
venv/Lib/site-packages/bleach/_vendor/html5lib/constants.py
venv/Lib/site-packages/bleach/_vendor/html5lib/html5parser.py
venv/Lib/site-packages/bleach/_vendor/html5lib/serializer.py
venv/Lib/site-packages/bleach/_vendor/html5lib/_trie/__init__.py
venv/Lib/site-packages/bleach/_vendor/html5lib/_trie/_base.py
venv/Lib/site-packages/bleach/_vendor/html5lib/_trie/py.py
venv/Lib/site-packages/bleach/_vendor/html5lib/filters/__init__.py
venv/Lib/site-packages/bleach/_vendor/html5lib/filters/alphabeticalattributes.py
venv/Lib/site-packages/bleach/_vendor/html5lib/filters/base.py
venv/Lib/site-packages/bleach/_vendor/html5lib/filters/inject_meta_charset.py
venv/Lib/site-packages/bleach/_vendor/html5lib/filters/lint.py
venv/Lib/site-packages/bleach/_vendor/html5lib/filters/optionaltags.py
venv/Lib/site-packages/bleach/_vendor/html5lib/filters/sanitizer.py
venv/Lib/site-packages/bleach/_vendor/html5lib/filters/whitespace.py
hmcalc-0.1.1.dist-info/LICENSE
hmcalc-0.1.1.dist-info/METADATA
hmcalc-0.1.1.dist-info/WHEEL
hmcalc-0.1.1.dist-info/top_level.txt
hmcalc-0.1.1.dist-info/RECORD
