Metadata-Version: 2.1
Name: hmcalc
Version: 0.1.1
Summary: Human-centered math utilities for change, comparison, trends and more
Author-email: Thendral Magudapathi <thendralmag@outlook.com>
License: MIT
Project-URL: Homepage, https://github.com/thendralmagudapathi/hmcalc_lib
Requires-Python: >=3.0
License-File: LICENSE
